{
 "standings": [
  {
   "lastAccept": 1573344534, 
   "pos": 1, 
   "score": 3061, 
   "taskStats": {
    "baby_recruiter": {
     "points": 293, 
     "time": 1573344534
    }, 
    "cloud_admin": {
     "points": 453, 
     "time": 1573250221
    }, 
    "full_troll": {
     "points": 243, 
     "time": 1573292124
    }, 
    "g00d_b0y": {
     "points": 84, 
     "time": 1573235615
    }, 
    "i_shall_never_be_anything": {
     "points": 308, 
     "time": 1573309748
    }, 
    "random_crypto": {
     "points": 435, 
     "time": 1573257061
    }, 
    "random_vault": {
     "points": 340, 
     "time": 1573303566
    }, 
    "rmbellious": {
     "points": 500, 
     "time": 1573324623
    }, 
    "roots_before_branches": {
     "points": 355, 
     "time": 1573331118
    }, 
    "the_last_resort": {
     "points": 50, 
     "time": 1573235386
    }
   }, 
   "team": "OpenToAll"
  }, 
  {
   "lastAccept": 1573329006, 
   "pos": 2, 
   "score": 3008, 
   "taskStats": {
    "full_troll": {
     "points": 243, 
     "time": 1573297906
    }, 
    "future_message_pt1": {
     "points": 314, 
     "time": 1573306326
    }, 
    "future_message_pt2": {
     "points": 420, 
     "time": 1573311608
    }, 
    "future_message_pt3": {
     "points": 420, 
     "time": 1573316547
    }, 
    "future_message_pt4": {
     "points": 474, 
     "time": 1573324228
    }, 
    "g00d_b0y": {
     "points": 84, 
     "time": 1573232182
    }, 
    "i_shall_never_be_anything": {
     "points": 308, 
     "time": 1573297409
    }, 
    "random_vault": {
     "points": 340, 
     "time": 1573329006
    }, 
    "roots_before_branches": {
     "points": 355, 
     "time": 1573303521
    }, 
    "the_last_resort": {
     "points": 50, 
     "time": 1573231332
    }
   }, 
   "team": "$wag"
  }, 
  {
   "lastAccept": 1573344701, 
   "pos": 3, 
   "score": 2827, 
   "taskStats": {
    "baby_recruiter": {
     "points": 293, 
     "time": 1573325518
    }, 
    "full_troll": {
     "points": 243, 
     "time": 1573274158
    }, 
    "future_message_pt1": {
     "points": 314, 
     "time": 1573267925
    }, 
    "future_message_pt2": {
     "points": 420, 
     "time": 1573332650
    }, 
    "future_message_pt3": {
     "points": 420, 
     "time": 1573344701
    }, 
    "g00d_b0y": {
     "points": 84, 
     "time": 1573235622
    }, 
    "i_shall_never_be_anything": {
     "points": 308, 
     "time": 1573339918
    }, 
    "random_vault": {
     "points": 340, 
     "time": 1573312350
    }, 
    "roots_before_branches": {
     "points": 355, 
     "time": 1573259032
    }, 
    "the_last_resort": {
     "points": 50, 
     "time": 1573235668
    }
   }, 
   "team": "FireShell"
  }, 
  {
   "lastAccept": 1573319300, 
   "pos": 4, 
   "score": 2700, 
   "taskStats": {
    "full_troll": {
     "points": 243, 
     "time": 1573239530
    }, 
    "future_message_pt1": {
     "points": 314, 
     "time": 1573246480
    }, 
    "future_message_pt2": {
     "points": 420, 
     "time": 1573257383
    }, 
    "future_message_pt3": {
     "points": 420, 
     "time": 1573260341
    }, 
    "future_message_pt4": {
     "points": 474, 
     "time": 1573319300
    }, 
    "g00d_b0y": {
     "points": 84, 
     "time": 1573236673
    }, 
    "random_vault": {
     "points": 340, 
     "time": 1573243403
    }, 
    "roots_before_branches": {
     "points": 355, 
     "time": 1573243507
    }, 
    "the_last_resort": {
     "points": 50, 
     "time": 1573237044
    }
   }, 
   "team": "RPISEC"
  }, 
  {
   "lastAccept": 1573341266, 
   "pos": 5, 
   "score": 2632, 
   "taskStats": {
    "baby_recruiter": {
     "points": 293, 
     "time": 1573339148
    }, 
    "cloud_admin": {
     "points": 453, 
     "time": 1573247229
    }, 
    "full_troll": {
     "points": 243, 
     "time": 1573319006
    }, 
    "future_message_pt1": {
     "points": 314, 
     "time": 1573341266
    }, 
    "g00d_b0y": {
     "points": 84, 
     "time": 1573240151
    }, 
    "matroska": {
     "points": 500, 
     "time": 1573332145
    }, 
    "random_vault": {
     "points": 340, 
     "time": 1573272164
    }, 
    "roots_before_branches": {
     "points": 355, 
     "time": 1573304226
    }, 
    "the_last_resort": {
     "points": 50, 
     "time": 1573233165
    }
   }, 
   "team": "justCatTheFish"
  }, 
  {
   "lastAccept": 1573309756, 
   "pos": 6, 
   "score": 2534, 
   "taskStats": {
    "full_troll": {
     "points": 243, 
     "time": 1573234004
    }, 
    "future_message_pt1": {
     "points": 314, 
     "time": 1573238181
    }, 
    "future_message_pt2": {
     "points": 420, 
     "time": 1573304720
    }, 
    "future_message_pt3": {
     "points": 420, 
     "time": 1573309756
    }, 
    "g00d_b0y": {
     "points": 84, 
     "time": 1573231449
    }, 
    "i_shall_never_be_anything": {
     "points": 308, 
     "time": 1573280833
    }, 
    "random_vault": {
     "points": 340, 
     "time": 1573239514
    }, 
    "roots_before_branches": {
     "points": 355, 
     "time": 1573283838
    }, 
    "the_last_resort": {
     "points": 50, 
     "time": 1573234123
    }
   }, 
   "team": "Balsn"
  }, 
  {
   "lastAccept": 1573310081, 
   "pos": 7, 
   "score": 2067, 
   "taskStats": {
    "baby_recruiter": {
     "points": 293, 
     "time": 1573310081
    }, 
    "full_troll": {
     "points": 243, 
     "time": 1573303581
    }, 
    "future_message_pt1": {
     "points": 314, 
     "time": 1573307916
    }, 
    "g00d_b0y": {
     "points": 84, 
     "time": 1573289051
    }, 
    "i_shall_never_be_anything": {
     "points": 308, 
     "time": 1573293341
    }, 
    "random_crypto": {
     "points": 435, 
     "time": 1573288913
    }, 
    "random_vault": {
     "points": 340, 
     "time": 1573288944
    }, 
    "the_last_resort": {
     "points": 50, 
     "time": 1573289023
    }
   }, 
   "team": "CL34R"
  }, 
  {
   "lastAccept": 1573321316, 
   "pos": 8, 
   "score": 1492, 
   "taskStats": {
    "full_troll": {
     "points": 243, 
     "time": 1573321316
    }, 
    "future_message_pt1": {
     "points": 314, 
     "time": 1573321087
    }, 
    "hardware_trojan_pt1": {
     "points": 500, 
     "time": 1573321015
    }, 
    "real_ec": {
     "points": 435, 
     "time": 1573321127
    }
   }, 
   "team": "dcua"
  }, 
  {
   "lastAccept": 1573324952, 
   "pos": 9, 
   "score": 1386, 
   "taskStats": {
    "full_troll": {
     "points": 243, 
     "time": 1573251448
    }, 
    "future_message_pt1": {
     "points": 314, 
     "time": 1573324952
    }, 
    "g00d_b0y": {
     "points": 84, 
     "time": 1573235169
    }, 
    "random_vault": {
     "points": 340, 
     "time": 1573264446
    }, 
    "roots_before_branches": {
     "points": 355, 
     "time": 1573317680
    }, 
    "the_last_resort": {
     "points": 50, 
     "time": 1573234722
    }
   }, 
   "team": "STT"
  }, 
  {
   "lastAccept": 1573336993, 
   "pos": 10, 
   "score": 1312, 
   "taskStats": {
    "g00d_b0y": {
     "points": 84, 
     "time": 1573233599
    }, 
    "i_shall_never_be_anything": {
     "points": 308, 
     "time": 1573336993
    }, 
    "random_crypto": {
     "points": 435, 
     "time": 1573327131
    }, 
    "real_ec": {
     "points": 435, 
     "time": 1573249940
    }, 
    "the_last_resort": {
     "points": 50, 
     "time": 1573232146
    }
   }, 
   "team": "mode13h"
  }, 
  {
   "lastAccept": 1573335957, 
   "pos": 11, 
   "score": 1288, 
   "taskStats": {
    "future_message_pt1": {
     "points": 314, 
     "time": 1573318213
    }, 
    "future_message_pt2": {
     "points": 420, 
     "time": 1573325720
    }, 
    "future_message_pt3": {
     "points": 420, 
     "time": 1573335957
    }, 
    "g00d_b0y": {
     "points": 84, 
     "time": 1573246963
    }, 
    "the_last_resort": {
     "points": 50, 
     "time": 1573247291
    }
   }, 
   "team": "Made In MIM"
  }, 
  {
   "lastAccept": 1573334686, 
   "pos": 12, 
   "score": 1277, 
   "taskStats": {
    "federated_sophia": {
     "points": 474, 
     "time": 1573333096
    }, 
    "future_message_pt1": {
     "points": 314, 
     "time": 1573334686
    }, 
    "g00d_b0y": {
     "points": 84, 
     "time": 1573299993
    }, 
    "roots_before_branches": {
     "points": 355, 
     "time": 1573307462
    }, 
    "the_last_resort": {
     "points": 50, 
     "time": 1573299913
    }
   }, 
   "team": "\ud835\ude65\ud835\ude5e\ud835\ude6f\ud835\ude6f\ud835\ude56\ud835\ude69\ud835\ude66\ud835\ude61 \u0295 \u2022\u0301\u0608\u2022\u0300)"
  }, 
  {
   "lastAccept": 1573326614, 
   "pos": 13, 
   "score": 1209, 
   "taskStats": {
    "baby_recruiter": {
     "points": 293, 
     "time": 1573293790
    }, 
    "federated_sophia": {
     "points": 474, 
     "time": 1573326614
    }, 
    "g00d_b0y": {
     "points": 84, 
     "time": 1573294341
    }, 
    "i_shall_never_be_anything": {
     "points": 308, 
     "time": 1573304656
    }, 
    "the_last_resort": {
     "points": 50, 
     "time": 1573294048
    }
   }, 
   "team": "vm00s3"
  }, 
  {
   "lastAccept": 1573333930, 
   "pos": 14, 
   "score": 1096, 
   "taskStats": {
    "baby_recruiter": {
     "points": 293, 
     "time": 1573333930
    }, 
    "future_message_pt1": {
     "points": 314, 
     "time": 1573304433
    }, 
    "g00d_b0y": {
     "points": 84, 
     "time": 1573231398
    }, 
    "roots_before_branches": {
     "points": 355, 
     "time": 1573245898
    }, 
    "the_last_resort": {
     "points": 50, 
     "time": 1573231346
    }
   }, 
   "team": "[USP] Ganesh"
  }, 
  {
   "lastAccept": 1573336196, 
   "pos": 15, 
   "score": 1090, 
   "taskStats": {
    "baby_recruiter": {
     "points": 293, 
     "time": 1573336196
    }, 
    "g00d_b0y": {
     "points": 84, 
     "time": 1573279739
    }, 
    "i_shall_never_be_anything": {
     "points": 308, 
     "time": 1573287427
    }, 
    "roots_before_branches": {
     "points": 355, 
     "time": 1573280244
    }, 
    "the_last_resort": {
     "points": 50, 
     "time": 1573266849
    }
   }, 
   "team": "Shellphish Grill Team"
  }, 
  {
   "lastAccept": 1573313247, 
   "pos": 16, 
   "score": 1025, 
   "taskStats": {
    "full_troll": {
     "points": 243, 
     "time": 1573248757
    }, 
    "g00d_b0y": {
     "points": 84, 
     "time": 1573232488
    }, 
    "i_shall_never_be_anything": {
     "points": 308, 
     "time": 1573313247
    }, 
    "random_vault": {
     "points": 340, 
     "time": 1573289119
    }, 
    "the_last_resort": {
     "points": 50, 
     "time": 1573231320
    }
   }, 
   "team": "LEGOFAN"
  }, 
  {
   "lastAccept": 1573313341, 
   "pos": 17, 
   "score": 1025, 
   "taskStats": {
    "full_troll": {
     "points": 243, 
     "time": 1573273571
    }, 
    "g00d_b0y": {
     "points": 84, 
     "time": 1573246861
    }, 
    "i_shall_never_be_anything": {
     "points": 308, 
     "time": 1573313341
    }, 
    "random_vault": {
     "points": 340, 
     "time": 1573302745
    }, 
    "the_last_resort": {
     "points": 50, 
     "time": 1573236011
    }
   }, 
   "team": "10sec"
  }, 
  {
   "lastAccept": 1573315311, 
   "pos": 18, 
   "score": 1010, 
   "taskStats": {
    "baby_recruiter": {
     "points": 293, 
     "time": 1573305348
    }, 
    "full_troll": {
     "points": 243, 
     "time": 1573305108
    }, 
    "g00d_b0y": {
     "points": 84, 
     "time": 1573306226
    }, 
    "random_vault": {
     "points": 340, 
     "time": 1573315311
    }, 
    "the_last_resort": {
     "points": 50, 
     "time": 1573295176
    }
   }, 
   "team": "pwntheTowerOfCrhackers"
  }, 
  {
   "lastAccept": 1573331724, 
   "pos": 19, 
   "score": 1010, 
   "taskStats": {
    "baby_recruiter": {
     "points": 293, 
     "time": 1573322982
    }, 
    "full_troll": {
     "points": 243, 
     "time": 1573246734
    }, 
    "g00d_b0y": {
     "points": 84, 
     "time": 1573232068
    }, 
    "random_vault": {
     "points": 340, 
     "time": 1573331724
    }, 
    "the_last_resort": {
     "points": 50, 
     "time": 1573231369
    }
   }, 
   "team": "NoPwnIntended"
  }, 
  {
   "lastAccept": 1573315065, 
   "pos": 20, 
   "score": 999, 
   "taskStats": {
    "full_troll": {
     "points": 243, 
     "time": 1573315065
    }, 
    "future_message_pt1": {
     "points": 314, 
     "time": 1573242319
    }, 
    "g00d_b0y": {
     "points": 84, 
     "time": 1573234691
    }, 
    "i_shall_never_be_anything": {
     "points": 308, 
     "time": 1573309546
    }, 
    "the_last_resort": {
     "points": 50, 
     "time": 1573233239
    }
   }, 
   "team": "shablul"
  }, 
  {
   "lastAccept": 1573341427, 
   "pos": 21, 
   "score": 947, 
   "taskStats": {
    "full_troll": {
     "points": 243, 
     "time": 1573302958
    }, 
    "future_message_pt1": {
     "points": 314, 
     "time": 1573341427
    }, 
    "random_vault": {
     "points": 340, 
     "time": 1573339593
    }, 
    "the_last_resort": {
     "points": 50, 
     "time": 1573340692
    }
   }, 
   "team": "The Flat Network Society"
  }, 
  {
   "lastAccept": 1573331617, 
   "pos": 22, 
   "score": 942, 
   "taskStats": {
    "g00d_b0y": {
     "points": 84, 
     "time": 1573231293
    }, 
    "i_shall_never_be_anything": {
     "points": 308, 
     "time": 1573266763
    }, 
    "the_last_resort": {
     "points": 50, 
     "time": 1573232244
    }, 
    "vamos_pra_russia": {
     "points": 500, 
     "time": 1573331617
    }
   }, 
   "team": "Alephfs"
  }, 
  {
   "lastAccept": 1573313739, 
   "pos": 23, 
   "score": 927, 
   "taskStats": {
    "astrobot": {
     "points": 500, 
     "time": 1573261706
    }, 
    "baby_recruiter": {
     "points": 293, 
     "time": 1573313739
    }, 
    "g00d_b0y": {
     "points": 84, 
     "time": 1573232011
    }, 
    "the_last_resort": {
     "points": 50, 
     "time": 1573231908
    }
   }, 
   "team": "MV9rwGOf08"
  }, 
  {
   "lastAccept": 1573264269, 
   "pos": 24, 
   "score": 830, 
   "taskStats": {
    "cloud_admin": {
     "points": 453, 
     "time": 1573255853
    }, 
    "full_troll": {
     "points": 243, 
     "time": 1573264269
    }, 
    "g00d_b0y": {
     "points": 84, 
     "time": 1573234626
    }, 
    "the_last_resort": {
     "points": 50, 
     "time": 1573234731
    }
   }, 
   "team": "[spbctf] fargate"
  }, 
  {
   "lastAccept": 1573303496, 
   "pos": 25, 
   "score": 735, 
   "taskStats": {
    "baby_recruiter": {
     "points": 293, 
     "time": 1573303496
    }, 
    "g00d_b0y": {
     "points": 84, 
     "time": 1573248084
    }, 
    "i_shall_never_be_anything": {
     "points": 308, 
     "time": 1573252744
    }, 
    "the_last_resort": {
     "points": 50, 
     "time": 1573234301
    }
   }, 
   "team": "room2042"
  }, 
  {
   "lastAccept": 1573339656, 
   "pos": 26, 
   "score": 735, 
   "taskStats": {
    "baby_recruiter": {
     "points": 293, 
     "time": 1573335535
    }, 
    "g00d_b0y": {
     "points": 84, 
     "time": 1573302167
    }, 
    "i_shall_never_be_anything": {
     "points": 308, 
     "time": 1573339656
    }, 
    "the_last_resort": {
     "points": 50, 
     "time": 1573293769
    }
   }, 
   "team": "vubar"
  }, 
  {
   "lastAccept": 1573300944, 
   "pos": 27, 
   "score": 691, 
   "taskStats": {
    "full_troll": {
     "points": 243, 
     "time": 1573285364
    }, 
    "future_message_pt1": {
     "points": 314, 
     "time": 1573300827
    }, 
    "g00d_b0y": {
     "points": 84, 
     "time": 1573300944
    }, 
    "the_last_resort": {
     "points": 50, 
     "time": 1573265479
    }
   }, 
   "team": "efiens"
  }, 
  {
   "lastAccept": 1573335098, 
   "pos": 28, 
   "score": 691, 
   "taskStats": {
    "full_troll": {
     "points": 243, 
     "time": 1573335098
    }, 
    "future_message_pt1": {
     "points": 314, 
     "time": 1573249792
    }, 
    "g00d_b0y": {
     "points": 84, 
     "time": 1573231639
    }, 
    "the_last_resort": {
     "points": 50, 
     "time": 1573231689
    }
   }, 
   "team": "teampowerprinter"
  }, 
  {
   "lastAccept": 1573274949, 
   "pos": 29, 
   "score": 685, 
   "taskStats": {
    "full_troll": {
     "points": 243, 
     "time": 1573273583
    }, 
    "g00d_b0y": {
     "points": 84, 
     "time": 1573249875
    }, 
    "i_shall_never_be_anything": {
     "points": 308, 
     "time": 1573274949
    }, 
    "the_last_resort": {
     "points": 50, 
     "time": 1573245268
    }
   }, 
   "team": "noraneco"
  }, 
  {
   "lastAccept": 1573276570, 
   "pos": 30, 
   "score": 685, 
   "taskStats": {
    "full_troll": {
     "points": 243, 
     "time": 1573268994
    }, 
    "g00d_b0y": {
     "points": 84, 
     "time": 1573276570
    }, 
    "i_shall_never_be_anything": {
     "points": 308, 
     "time": 1573274454
    }, 
    "the_last_resort": {
     "points": 50, 
     "time": 1573237467
    }
   }, 
   "team": "pwndevils"
  }, 
  {
   "lastAccept": 1573310821, 
   "pos": 31, 
   "score": 685, 
   "taskStats": {
    "full_troll": {
     "points": 243, 
     "time": 1573310821
    }, 
    "g00d_b0y": {
     "points": 84, 
     "time": 1573305671
    }, 
    "i_shall_never_be_anything": {
     "points": 308, 
     "time": 1573309555
    }, 
    "the_last_resort": {
     "points": 50, 
     "time": 1573295559
    }
   }, 
   "team": "Mbelgedes"
  }, 
  {
   "lastAccept": 1573308538, 
   "pos": 32, 
   "score": 670, 
   "taskStats": {
    "baby_recruiter": {
     "points": 293, 
     "time": 1573308538
    }, 
    "full_troll": {
     "points": 243, 
     "time": 1573294133
    }, 
    "g00d_b0y": {
     "points": 84, 
     "time": 1573294181
    }, 
    "the_last_resort": {
     "points": 50, 
     "time": 1573294067
    }
   }, 
   "team": "Spotless"
  }, 
  {
   "lastAccept": 1573334213, 
   "pos": 33, 
   "score": 670, 
   "taskStats": {
    "baby_recruiter": {
     "points": 293, 
     "time": 1573316630
    }, 
    "full_troll": {
     "points": 243, 
     "time": 1573268661
    }, 
    "g00d_b0y": {
     "points": 84, 
     "time": 1573334213
    }, 
    "the_last_resort": {
     "points": 50, 
     "time": 1573238878
    }
   }, 
   "team": "ROPperoni"
  }, 
  {
   "lastAccept": 1573327011, 
   "pos": 34, 
   "score": 569, 
   "taskStats": {
    "g00d_b0y": {
     "points": 84, 
     "time": 1573326667
    }, 
    "real_ec": {
     "points": 435, 
     "time": 1573327011
    }, 
    "the_last_resort": {
     "points": 50, 
     "time": 1573326354
    }
   }, 
   "team": "t"
  }, 
  {
   "lastAccept": 1573282762, 
   "pos": 35, 
   "score": 489, 
   "taskStats": {
    "g00d_b0y": {
     "points": 84, 
     "time": 1573231985
    }, 
    "roots_before_branches": {
     "points": 355, 
     "time": 1573282762
    }, 
    "the_last_resort": {
     "points": 50, 
     "time": 1573232289
    }
   }, 
   "team": "Shingeki_No_Chikungunya"
  }, 
  {
   "lastAccept": 1573319944, 
   "pos": 36, 
   "score": 485, 
   "taskStats": {
    "random_crypto": {
     "points": 435, 
     "time": 1573319944
    }, 
    "the_last_resort": {
     "points": 50, 
     "time": 1573262837
    }
   }, 
   "team": "polygl0ts"
  }, 
  {
   "lastAccept": 1573324488, 
   "pos": 37, 
   "score": 485, 
   "taskStats": {
    "real_ec": {
     "points": 435, 
     "time": 1573324488
    }, 
    "the_last_resort": {
     "points": 50, 
     "time": 1573261489
    }
   }, 
   "team": "Kernel Sanders,"
  }, 
  {
   "lastAccept": 1573312673, 
   "pos": 38, 
   "score": 427, 
   "taskStats": {
    "baby_recruiter": {
     "points": 293, 
     "time": 1573312673
    }, 
    "g00d_b0y": {
     "points": 84, 
     "time": 1573232089
    }, 
    "the_last_resort": {
     "points": 50, 
     "time": 1573235957
    }
   }, 
   "team": "Ridiculous Burping Trumpets"
  }, 
  {
   "lastAccept": 1573316280, 
   "pos": 39, 
   "score": 427, 
   "taskStats": {
    "baby_recruiter": {
     "points": 293, 
     "time": 1573316280
    }, 
    "g00d_b0y": {
     "points": 84, 
     "time": 1573231619
    }, 
    "the_last_resort": {
     "points": 50, 
     "time": 1573231405
    }
   }, 
   "team": "flagbot"
  }, 
  {
   "lastAccept": 1573317875, 
   "pos": 40, 
   "score": 427, 
   "taskStats": {
    "baby_recruiter": {
     "points": 293, 
     "time": 1573317875
    }, 
    "g00d_b0y": {
     "points": 84, 
     "time": 1573231640
    }, 
    "the_last_resort": {
     "points": 50, 
     "time": 1573231751
    }
   }, 
   "team": "VSCOPWN"
  }, 
  {
   "lastAccept": 1573329139, 
   "pos": 41, 
   "score": 427, 
   "taskStats": {
    "baby_recruiter": {
     "points": 293, 
     "time": 1573329139
    }, 
    "g00d_b0y": {
     "points": 84, 
     "time": 1573232974
    }, 
    "the_last_resort": {
     "points": 50, 
     "time": 1573231373
    }
   }, 
   "team": "SIGFLAG"
  }, 
  {
   "lastAccept": 1573336741, 
   "pos": 42, 
   "score": 427, 
   "taskStats": {
    "baby_recruiter": {
     "points": 293, 
     "time": 1573336741
    }, 
    "g00d_b0y": {
     "points": 84, 
     "time": 1573335788
    }, 
    "the_last_resort": {
     "points": 50, 
     "time": 1573336111
    }
   }, 
   "team": "Donnacona-Hochelaga"
  }, 
  {
   "lastAccept": 1573290287, 
   "pos": 43, 
   "score": 398, 
   "taskStats": {
    "future_message_pt1": {
     "points": 314, 
     "time": 1573290287
    }, 
    "g00d_b0y": {
     "points": 84, 
     "time": 1573233486
    }
   }, 
   "team": "Harekaze"
  }, 
  {
   "lastAccept": 1573254269, 
   "pos": 44, 
   "score": 377, 
   "taskStats": {
    "full_troll": {
     "points": 243, 
     "time": 1573252690
    }, 
    "g00d_b0y": {
     "points": 84, 
     "time": 1573254269
    }, 
    "the_last_resort": {
     "points": 50, 
     "time": 1573240184
    }
   }, 
   "team": "PwnaSonic"
  }, 
  {
   "lastAccept": 1573256190, 
   "pos": 45, 
   "score": 377, 
   "taskStats": {
    "full_troll": {
     "points": 243, 
     "time": 1573256190
    }, 
    "g00d_b0y": {
     "points": 84, 
     "time": 1573231720
    }, 
    "the_last_resort": {
     "points": 50, 
     "time": 1573231606
    }
   }, 
   "team": "RevEng"
  }, 
  {
   "lastAccept": 1573273540, 
   "pos": 46, 
   "score": 377, 
   "taskStats": {
    "full_troll": {
     "points": 243, 
     "time": 1573273060
    }, 
    "g00d_b0y": {
     "points": 84, 
     "time": 1573273540
    }, 
    "the_last_resort": {
     "points": 50, 
     "time": 1573267706
    }
   }, 
   "team": "timHehe"
  }, 
  {
   "lastAccept": 1573274298, 
   "pos": 47, 
   "score": 377, 
   "taskStats": {
    "full_troll": {
     "points": 243, 
     "time": 1573274298
    }, 
    "g00d_b0y": {
     "points": 84, 
     "time": 1573232019
    }, 
    "the_last_resort": {
     "points": 50, 
     "time": 1573231370
    }
   }, 
   "team": "******"
  }, 
  {
   "lastAccept": 1573289618, 
   "pos": 48, 
   "score": 377, 
   "taskStats": {
    "full_troll": {
     "points": 243, 
     "time": 1573289618
    }, 
    "g00d_b0y": {
     "points": 84, 
     "time": 1573241820
    }, 
    "the_last_resort": {
     "points": 50, 
     "time": 1573238106
    }
   }, 
   "team": "CSI"
  }, 
  {
   "lastAccept": 1573329250, 
   "pos": 49, 
   "score": 377, 
   "taskStats": {
    "full_troll": {
     "points": 243, 
     "time": 1573329250
    }, 
    "g00d_b0y": {
     "points": 84, 
     "time": 1573315646
    }, 
    "the_last_resort": {
     "points": 50, 
     "time": 1573315555
    }
   }, 
   "team": "TeamRocketIst"
  }, 
  {
   "lastAccept": 1573329851, 
   "pos": 50, 
   "score": 377, 
   "taskStats": {
    "full_troll": {
     "points": 243, 
     "time": 1573329851
    }, 
    "g00d_b0y": {
     "points": 84, 
     "time": 1573232684
    }, 
    "the_last_resort": {
     "points": 50, 
     "time": 1573231383
    }
   }, 
   "team": "LTLUO + 1"
  }, 
  {
   "lastAccept": 1573336093, 
   "pos": 51, 
   "score": 377, 
   "taskStats": {
    "full_troll": {
     "points": 243, 
     "time": 1573336093
    }, 
    "g00d_b0y": {
     "points": 84, 
     "time": 1573239692
    }, 
    "the_last_resort": {
     "points": 50, 
     "time": 1573238446
    }
   }, 
   "team": "fr3nzy"
  }, 
  {
   "lastAccept": 1573342089, 
   "pos": 52, 
   "score": 364, 
   "taskStats": {
    "future_message_pt1": {
     "points": 314, 
     "time": 1573342089
    }, 
    "the_last_resort": {
     "points": 50, 
     "time": 1573313010
    }
   }, 
   "team": "YoloSw4g"
  }, 
  {
   "lastAccept": 1573279377, 
   "pos": 53, 
   "score": 358, 
   "taskStats": {
    "i_shall_never_be_anything": {
     "points": 308, 
     "time": 1573277540
    }, 
    "the_last_resort": {
     "points": 50, 
     "time": 1573279377
    }
   }, 
   "team": "nizkkk"
  }, 
  {
   "lastAccept": 1573303881, 
   "pos": 54, 
   "score": 343, 
   "taskStats": {
    "baby_recruiter": {
     "points": 293, 
     "time": 1573303546
    }, 
    "the_last_resort": {
     "points": 50, 
     "time": 1573303881
    }
   }, 
   "team": "entr0py"
  }, 
  {
   "lastAccept": 1573312902, 
   "pos": 55, 
   "score": 293, 
   "taskStats": {
    "full_troll": {
     "points": 243, 
     "time": 1573312467
    }, 
    "the_last_resort": {
     "points": 50, 
     "time": 1573312902
    }
   }, 
   "team": "Mashiro"
  }, 
  {
   "lastAccept": 1573348175, 
   "pos": 56, 
   "score": 293, 
   "taskStats": {
    "baby_recruiter": {
     "points": 293, 
     "time": 1573348175
    }
   }, 
   "team": "Nupakachi"
  }, 
  {
   "lastAccept": 1573320512, 
   "pos": 57, 
   "score": 243, 
   "taskStats": {
    "full_troll": {
     "points": 243, 
     "time": 1573320512
    }
   }, 
   "team": "TeamC8"
  }, 
  {
   "lastAccept": 1573345684, 
   "pos": 58, 
   "score": 243, 
   "taskStats": {
    "full_troll": {
     "points": 243, 
     "time": 1573345684
    }
   }, 
   "team": "Dashu"
  }, 
  {
   "lastAccept": 1573231287, 
   "pos": 59, 
   "score": 134, 
   "taskStats": {
    "g00d_b0y": {
     "points": 84, 
     "time": 1573231333
    }, 
    "the_last_resort": {
     "points": 50, 
     "time": 1573231287
    }
   }, 
   "team": "RedGKFRocket"
  }, 
  {
   "lastAccept": 1573231385, 
   "pos": 60, 
   "score": 134, 
   "taskStats": {
    "g00d_b0y": {
     "points": 84, 
     "time": 1573231098
    }, 
    "the_last_resort": {
     "points": 50, 
     "time": 1573231385
    }
   }, 
   "team": "Ne0Lux-C1Ph3r"
  }, 
  {
   "lastAccept": 1573231432, 
   "pos": 61, 
   "score": 134, 
   "taskStats": {
    "g00d_b0y": {
     "points": 84, 
     "time": 1573231528
    }, 
    "the_last_resort": {
     "points": 50, 
     "time": 1573231432
    }
   }, 
   "team": "rfid-171"
  }, 
  {
   "lastAccept": 1573231501, 
   "pos": 62, 
   "score": 134, 
   "taskStats": {
    "g00d_b0y": {
     "points": 84, 
     "time": 1573231501
    }, 
    "the_last_resort": {
     "points": 50, 
     "time": 1573231196
    }
   }, 
   "team": "Zemows Industries"
  }, 
  {
   "lastAccept": 1573231520, 
   "pos": 63, 
   "score": 134, 
   "taskStats": {
    "g00d_b0y": {
     "points": 84, 
     "time": 1573231309
    }, 
    "the_last_resort": {
     "points": 50, 
     "time": 1573231520
    }
   }, 
   "team": "ThePhills"
  }, 
  {
   "lastAccept": 1573231583, 
   "pos": 64, 
   "score": 134, 
   "taskStats": {
    "g00d_b0y": {
     "points": 84, 
     "time": 1573231422
    }, 
    "the_last_resort": {
     "points": 50, 
     "time": 1573231583
    }
   }, 
   "team": "TheF0rce"
  }, 
  {
   "lastAccept": 1573231603, 
   "pos": 65, 
   "score": 134, 
   "taskStats": {
    "g00d_b0y": {
     "points": 84, 
     "time": 1573231411
    }, 
    "the_last_resort": {
     "points": 50, 
     "time": 1573231603
    }
   }, 
   "team": "CSI_Inatel"
  }, 
  {
   "lastAccept": 1573231629, 
   "pos": 66, 
   "score": 134, 
   "taskStats": {
    "g00d_b0y": {
     "points": 84, 
     "time": 1573231629
    }, 
    "the_last_resort": {
     "points": 50, 
     "time": 1573231473
    }
   }, 
   "team": "technic"
  }, 
  {
   "lastAccept": 1573231792, 
   "pos": 67, 
   "score": 134, 
   "taskStats": {
    "g00d_b0y": {
     "points": 84, 
     "time": 1573231792
    }, 
    "the_last_resort": {
     "points": 50, 
     "time": 1573231604
    }
   }, 
   "team": "MiloTruck"
  }, 
  {
   "lastAccept": 1573231833, 
   "pos": 68, 
   "score": 134, 
   "taskStats": {
    "g00d_b0y": {
     "points": 84, 
     "time": 1573231833
    }, 
    "the_last_resort": {
     "points": 50, 
     "time": 1573231558
    }
   }, 
   "team": "NSI"
  }, 
  {
   "lastAccept": 1573231995, 
   "pos": 69, 
   "score": 134, 
   "taskStats": {
    "g00d_b0y": {
     "points": 84, 
     "time": 1573232443
    }, 
    "the_last_resort": {
     "points": 50, 
     "time": 1573231995
    }
   }, 
   "team": "Bisounours"
  }, 
  {
   "lastAccept": 1573232211, 
   "pos": 70, 
   "score": 134, 
   "taskStats": {
    "g00d_b0y": {
     "points": 84, 
     "time": 1573233432
    }, 
    "the_last_resort": {
     "points": 50, 
     "time": 1573232211
    }
   }, 
   "team": "MengtheMerciless"
  }, 
  {
   "lastAccept": 1573232238, 
   "pos": 71, 
   "score": 134, 
   "taskStats": {
    "g00d_b0y": {
     "points": 84, 
     "time": 1573231669
    }, 
    "the_last_resort": {
     "points": 50, 
     "time": 1573232238
    }
   }, 
   "team": "Shellmates JR"
  }, 
  {
   "lastAccept": 1573232276, 
   "pos": 72, 
   "score": 134, 
   "taskStats": {
    "g00d_b0y": {
     "points": 84, 
     "time": 1573232276
    }, 
    "the_last_resort": {
     "points": 50, 
     "time": 1573231539
    }
   }, 
   "team": "RATF"
  }, 
  {
   "lastAccept": 1573232547, 
   "pos": 73, 
   "score": 134, 
   "taskStats": {
    "g00d_b0y": {
     "points": 84, 
     "time": 1573232547
    }, 
    "the_last_resort": {
     "points": 50, 
     "time": 1573231662
    }
   }, 
   "team": "errant_cattus"
  }, 
  {
   "lastAccept": 1573232559, 
   "pos": 74, 
   "score": 134, 
   "taskStats": {
    "g00d_b0y": {
     "points": 84, 
     "time": 1573232559
    }, 
    "the_last_resort": {
     "points": 50, 
     "time": 1573232417
    }
   }, 
   "team": "simon"
  }, 
  {
   "lastAccept": 1573232618, 
   "pos": 75, 
   "score": 134, 
   "taskStats": {
    "g00d_b0y": {
     "points": 84, 
     "time": 1573232618
    }, 
    "the_last_resort": {
     "points": 50, 
     "time": 1573231711
    }
   }, 
   "team": "GR00T5"
  }, 
  {
   "lastAccept": 1573233062, 
   "pos": 76, 
   "score": 134, 
   "taskStats": {
    "g00d_b0y": {
     "points": 84, 
     "time": 1573233062
    }, 
    "the_last_resort": {
     "points": 50, 
     "time": 1573232372
    }
   }, 
   "team": "KUDoS"
  }, 
  {
   "lastAccept": 1573233273, 
   "pos": 77, 
   "score": 134, 
   "taskStats": {
    "g00d_b0y": {
     "points": 84, 
     "time": 1573233273
    }, 
    "the_last_resort": {
     "points": 50, 
     "time": 1573233201
    }
   }, 
   "team": "Blaze Raptors"
  }, 
  {
   "lastAccept": 1573233378, 
   "pos": 78, 
   "score": 134, 
   "taskStats": {
    "g00d_b0y": {
     "points": 84, 
     "time": 1573233378
    }, 
    "the_last_resort": {
     "points": 50, 
     "time": 1573233305
    }
   }, 
   "team": "{sig_0ct4nt15}"
  }, 
  {
   "lastAccept": 1573233409, 
   "pos": 79, 
   "score": 134, 
   "taskStats": {
    "g00d_b0y": {
     "points": 84, 
     "time": 1573233409
    }, 
    "the_last_resort": {
     "points": 50, 
     "time": 1573233335
    }
   }, 
   "team": "lonich"
  }, 
  {
   "lastAccept": 1573233529, 
   "pos": 80, 
   "score": 134, 
   "taskStats": {
    "g00d_b0y": {
     "points": 84, 
     "time": 1573233529
    }, 
    "the_last_resort": {
     "points": 50, 
     "time": 1573232872
    }
   }, 
   "team": "nn13"
  }, 
  {
   "lastAccept": 1573234090, 
   "pos": 81, 
   "score": 134, 
   "taskStats": {
    "g00d_b0y": {
     "points": 84, 
     "time": 1573233695
    }, 
    "the_last_resort": {
     "points": 50, 
     "time": 1573234090
    }
   }, 
   "team": "pastelteam"
  }, 
  {
   "lastAccept": 1573234344, 
   "pos": 82, 
   "score": 134, 
   "taskStats": {
    "g00d_b0y": {
     "points": 84, 
     "time": 1573234344
    }, 
    "the_last_resort": {
     "points": 50, 
     "time": 1573232540
    }
   }, 
   "team": "Deadlock"
  }, 
  {
   "lastAccept": 1573235050, 
   "pos": 83, 
   "score": 134, 
   "taskStats": {
    "g00d_b0y": {
     "points": 84, 
     "time": 1573233364
    }, 
    "the_last_resort": {
     "points": 50, 
     "time": 1573235050
    }
   }, 
   "team": "Server"
  }, 
  {
   "lastAccept": 1573235976, 
   "pos": 84, 
   "score": 134, 
   "taskStats": {
    "g00d_b0y": {
     "points": 84, 
     "time": 1573235976
    }, 
    "the_last_resort": {
     "points": 50, 
     "time": 1573235640
    }
   }, 
   "team": "Kurisutina"
  }, 
  {
   "lastAccept": 1573236791, 
   "pos": 85, 
   "score": 134, 
   "taskStats": {
    "g00d_b0y": {
     "points": 84, 
     "time": 1573236791
    }, 
    "the_last_resort": {
     "points": 50, 
     "time": 1573235604
    }
   }, 
   "team": "spoilers"
  }, 
  {
   "lastAccept": 1573236906, 
   "pos": 86, 
   "score": 134, 
   "taskStats": {
    "g00d_b0y": {
     "points": 84, 
     "time": 1573236906
    }, 
    "the_last_resort": {
     "points": 50, 
     "time": 1573235923
    }
   }, 
   "team": "Armitage Team"
  }, 
  {
   "lastAccept": 1573237317, 
   "pos": 87, 
   "score": 134, 
   "taskStats": {
    "g00d_b0y": {
     "points": 84, 
     "time": 1573237317
    }, 
    "the_last_resort": {
     "points": 50, 
     "time": 1573235005
    }
   }, 
   "team": "allalone"
  }, 
  {
   "lastAccept": 1573237744, 
   "pos": 88, 
   "score": 134, 
   "taskStats": {
    "g00d_b0y": {
     "points": 84, 
     "time": 1573237722
    }, 
    "the_last_resort": {
     "points": 50, 
     "time": 1573237744
    }
   }, 
   "team": "SAL"
  }, 
  {
   "lastAccept": 1573237782, 
   "pos": 89, 
   "score": 134, 
   "taskStats": {
    "g00d_b0y": {
     "points": 84, 
     "time": 1573236225
    }, 
    "the_last_resort": {
     "points": 50, 
     "time": 1573237782
    }
   }, 
   "team": "InstructionsNotClear"
  }, 
  {
   "lastAccept": 1573237844, 
   "pos": 90, 
   "score": 134, 
   "taskStats": {
    "g00d_b0y": {
     "points": 84, 
     "time": 1573237844
    }, 
    "the_last_resort": {
     "points": 50, 
     "time": 1573231423
    }
   }, 
   "team": "Heroes Cyber Security"
  }, 
  {
   "lastAccept": 1573238059, 
   "pos": 91, 
   "score": 134, 
   "taskStats": {
    "g00d_b0y": {
     "points": 84, 
     "time": 1573238059
    }, 
    "the_last_resort": {
     "points": 50, 
     "time": 1573232379
    }
   }, 
   "team": "smopper"
  }, 
  {
   "lastAccept": 1573238532, 
   "pos": 92, 
   "score": 134, 
   "taskStats": {
    "g00d_b0y": {
     "points": 84, 
     "time": 1573238532
    }, 
    "the_last_resort": {
     "points": 50, 
     "time": 1573238263
    }
   }, 
   "team": "Team Rokek"
  }, 
  {
   "lastAccept": 1573239319, 
   "pos": 93, 
   "score": 134, 
   "taskStats": {
    "g00d_b0y": {
     "points": 84, 
     "time": 1573239319
    }, 
    "the_last_resort": {
     "points": 50, 
     "time": 1573231466
    }
   }, 
   "team": "bluehens"
  }, 
  {
   "lastAccept": 1573239603, 
   "pos": 94, 
   "score": 134, 
   "taskStats": {
    "g00d_b0y": {
     "points": 84, 
     "time": 1573239603
    }, 
    "the_last_resort": {
     "points": 50, 
     "time": 1573239157
    }
   }, 
   "team": "wr47h"
  }, 
  {
   "lastAccept": 1573241473, 
   "pos": 95, 
   "score": 134, 
   "taskStats": {
    "g00d_b0y": {
     "points": 84, 
     "time": 1573241473
    }, 
    "the_last_resort": {
     "points": 50, 
     "time": 1573241268
    }
   }, 
   "team": "Killer Queen"
  }, 
  {
   "lastAccept": 1573241634, 
   "pos": 96, 
   "score": 134, 
   "taskStats": {
    "g00d_b0y": {
     "points": 84, 
     "time": 1573241634
    }, 
    "the_last_resort": {
     "points": 50, 
     "time": 1573238899
    }
   }, 
   "team": "Avengers"
  }, 
  {
   "lastAccept": 1573241673, 
   "pos": 97, 
   "score": 134, 
   "taskStats": {
    "g00d_b0y": {
     "points": 84, 
     "time": 1573241260
    }, 
    "the_last_resort": {
     "points": 50, 
     "time": 1573241673
    }
   }, 
   "team": "404NotFound"
  }, 
  {
   "lastAccept": 1573241746, 
   "pos": 98, 
   "score": 134, 
   "taskStats": {
    "g00d_b0y": {
     "points": 84, 
     "time": 1573241746
    }, 
    "the_last_resort": {
     "points": 50, 
     "time": 1573241353
    }
   }, 
   "team": "Chinchila"
  }, 
  {
   "lastAccept": 1573241840, 
   "pos": 99, 
   "score": 134, 
   "taskStats": {
    "g00d_b0y": {
     "points": 84, 
     "time": 1573241840
    }, 
    "the_last_resort": {
     "points": 50, 
     "time": 1573240913
    }
   }, 
   "team": "PelarianCP"
  }, 
  {
   "lastAccept": 1573242501, 
   "pos": 100, 
   "score": 134, 
   "taskStats": {
    "g00d_b0y": {
     "points": 84, 
     "time": 1573242501
    }, 
    "the_last_resort": {
     "points": 50, 
     "time": 1573242081
    }
   }, 
   "team": "Bas3Camp"
  }, 
  {
   "lastAccept": 1573243039, 
   "pos": 101, 
   "score": 134, 
   "taskStats": {
    "g00d_b0y": {
     "points": 84, 
     "time": 1573236966
    }, 
    "the_last_resort": {
     "points": 50, 
     "time": 1573243039
    }
   }, 
   "team": "deathsquad"
  }, 
  {
   "lastAccept": 1573244406, 
   "pos": 102, 
   "score": 134, 
   "taskStats": {
    "g00d_b0y": {
     "points": 84, 
     "time": 1573244406
    }, 
    "the_last_resort": {
     "points": 50, 
     "time": 1573244331
    }
   }, 
   "team": "PretentiousTeamName"
  }, 
  {
   "lastAccept": 1573244545, 
   "pos": 103, 
   "score": 134, 
   "taskStats": {
    "g00d_b0y": {
     "points": 84, 
     "time": 1573244545
    }, 
    "the_last_resort": {
     "points": 50, 
     "time": 1573244391
    }
   }, 
   "team": "JohnPwnJones"
  }, 
  {
   "lastAccept": 1573244994, 
   "pos": 104, 
   "score": 134, 
   "taskStats": {
    "g00d_b0y": {
     "points": 84, 
     "time": 1573244878
    }, 
    "the_last_resort": {
     "points": 50, 
     "time": 1573244994
    }
   }, 
   "team": "?"
  }, 
  {
   "lastAccept": 1573245630, 
   "pos": 105, 
   "score": 134, 
   "taskStats": {
    "g00d_b0y": {
     "points": 84, 
     "time": 1573245630
    }, 
    "the_last_resort": {
     "points": 50, 
     "time": 1573245542
    }
   }, 
   "team": "HDRN"
  }, 
  {
   "lastAccept": 1573245979, 
   "pos": 106, 
   "score": 134, 
   "taskStats": {
    "g00d_b0y": {
     "points": 84, 
     "time": 1573245979
    }, 
    "the_last_resort": {
     "points": 50, 
     "time": 1573242789
    }
   }, 
   "team": "unauthorized"
  }, 
  {
   "lastAccept": 1573246176, 
   "pos": 107, 
   "score": 134, 
   "taskStats": {
    "g00d_b0y": {
     "points": 84, 
     "time": 1573246176
    }, 
    "the_last_resort": {
     "points": 50, 
     "time": 1573235874
    }
   }, 
   "team": "RobotMafia"
  }, 
  {
   "lastAccept": 1573246847, 
   "pos": 108, 
   "score": 134, 
   "taskStats": {
    "g00d_b0y": {
     "points": 84, 
     "time": 1573244601
    }, 
    "the_last_resort": {
     "points": 50, 
     "time": 1573246847
    }
   }, 
   "team": "Denhac"
  }, 
  {
   "lastAccept": 1573246872, 
   "pos": 109, 
   "score": 134, 
   "taskStats": {
    "g00d_b0y": {
     "points": 84, 
     "time": 1573246872
    }, 
    "the_last_resort": {
     "points": 50, 
     "time": 1573245136
    }
   }, 
   "team": "M.5453"
  }, 
  {
   "lastAccept": 1573247033, 
   "pos": 110, 
   "score": 134, 
   "taskStats": {
    "g00d_b0y": {
     "points": 84, 
     "time": 1573247033
    }, 
    "the_last_resort": {
     "points": 50, 
     "time": 1573246879
    }
   }, 
   "team": "stankc"
  }, 
  {
   "lastAccept": 1573247082, 
   "pos": 111, 
   "score": 134, 
   "taskStats": {
    "g00d_b0y": {
     "points": 84, 
     "time": 1573247082
    }, 
    "the_last_resort": {
     "points": 50, 
     "time": 1573235739
    }
   }, 
   "team": "Raccoons"
  }, 
  {
   "lastAccept": 1573248832, 
   "pos": 112, 
   "score": 134, 
   "taskStats": {
    "g00d_b0y": {
     "points": 84, 
     "time": 1573248832
    }, 
    "the_last_resort": {
     "points": 50, 
     "time": 1573248311
    }
   }, 
   "team": "K1_W4L0"
  }, 
  {
   "lastAccept": 1573249663, 
   "pos": 113, 
   "score": 134, 
   "taskStats": {
    "g00d_b0y": {
     "points": 84, 
     "time": 1573249663
    }, 
    "the_last_resort": {
     "points": 50, 
     "time": 1573249465
    }
   }, 
   "team": "Lost in Bytes"
  }, 
  {
   "lastAccept": 1573250701, 
   "pos": 114, 
   "score": 134, 
   "taskStats": {
    "g00d_b0y": {
     "points": 84, 
     "time": 1573250701
    }, 
    "the_last_resort": {
     "points": 50, 
     "time": 1573248215
    }
   }, 
   "team": "Z4HYA_Lo0t"
  }, 
  {
   "lastAccept": 1573251061, 
   "pos": 115, 
   "score": 134, 
   "taskStats": {
    "g00d_b0y": {
     "points": 84, 
     "time": 1573250693
    }, 
    "the_last_resort": {
     "points": 50, 
     "time": 1573251061
    }
   }, 
   "team": "theBoloys"
  }, 
  {
   "lastAccept": 1573252865, 
   "pos": 116, 
   "score": 134, 
   "taskStats": {
    "g00d_b0y": {
     "points": 84, 
     "time": 1573252865
    }, 
    "the_last_resort": {
     "points": 50, 
     "time": 1573242544
    }
   }, 
   "team": "Watson"
  }, 
  {
   "lastAccept": 1573253252, 
   "pos": 117, 
   "score": 134, 
   "taskStats": {
    "g00d_b0y": {
     "points": 84, 
     "time": 1573253252
    }, 
    "the_last_resort": {
     "points": 50, 
     "time": 1573253198
    }
   }, 
   "team": "Nibbles@UFRPE"
  }, 
  {
   "lastAccept": 1573253421, 
   "pos": 118, 
   "score": 134, 
   "taskStats": {
    "g00d_b0y": {
     "points": 84, 
     "time": 1573253421
    }, 
    "the_last_resort": {
     "points": 50, 
     "time": 1573249161
    }
   }, 
   "team": "AGEEI_Crew"
  }, 
  {
   "lastAccept": 1573255565, 
   "pos": 119, 
   "score": 134, 
   "taskStats": {
    "g00d_b0y": {
     "points": 84, 
     "time": 1573255565
    }, 
    "the_last_resort": {
     "points": 50, 
     "time": 1573255170
    }
   }, 
   "team": "blueship"
  }, 
  {
   "lastAccept": 1573255842, 
   "pos": 120, 
   "score": 134, 
   "taskStats": {
    "g00d_b0y": {
     "points": 84, 
     "time": 1573255662
    }, 
    "the_last_resort": {
     "points": 50, 
     "time": 1573255842
    }
   }, 
   "team": "Notorious Hunters"
  }, 
  {
   "lastAccept": 1573259264, 
   "pos": 121, 
   "score": 134, 
   "taskStats": {
    "g00d_b0y": {
     "points": 84, 
     "time": 1573259200
    }, 
    "the_last_resort": {
     "points": 50, 
     "time": 1573259264
    }
   }, 
   "team": "cyclones"
  }, 
  {
   "lastAccept": 1573259603, 
   "pos": 122, 
   "score": 134, 
   "taskStats": {
    "g00d_b0y": {
     "points": 84, 
     "time": 1573259603
    }, 
    "the_last_resort": {
     "points": 50, 
     "time": 1573258682
    }
   }, 
   "team": "CST-UTM"
  }, 
  {
   "lastAccept": 1573260253, 
   "pos": 123, 
   "score": 134, 
   "taskStats": {
    "g00d_b0y": {
     "points": 84, 
     "time": 1573260253
    }, 
    "the_last_resort": {
     "points": 50, 
     "time": 1573236002
    }
   }, 
   "team": "Bushwhackers"
  }, 
  {
   "lastAccept": 1573260512, 
   "pos": 124, 
   "score": 134, 
   "taskStats": {
    "g00d_b0y": {
     "points": 84, 
     "time": 1573260512
    }, 
    "the_last_resort": {
     "points": 50, 
     "time": 1573254754
    }
   }, 
   "team": "Clever Crow"
  }, 
  {
   "lastAccept": 1573262226, 
   "pos": 125, 
   "score": 134, 
   "taskStats": {
    "g00d_b0y": {
     "points": 84, 
     "time": 1573244338
    }, 
    "the_last_resort": {
     "points": 50, 
     "time": 1573262226
    }
   }, 
   "team": "RTFM"
  }, 
  {
   "lastAccept": 1573262325, 
   "pos": 126, 
   "score": 134, 
   "taskStats": {
    "g00d_b0y": {
     "points": 84, 
     "time": 1573262325
    }, 
    "the_last_resort": {
     "points": 50, 
     "time": 1573261451
    }
   }, 
   "team": "GS2W"
  }, 
  {
   "lastAccept": 1573263379, 
   "pos": 127, 
   "score": 134, 
   "taskStats": {
    "g00d_b0y": {
     "points": 84, 
     "time": 1573245392
    }, 
    "the_last_resort": {
     "points": 50, 
     "time": 1573263379
    }
   }, 
   "team": "TheScottish"
  }, 
  {
   "lastAccept": 1573264485, 
   "pos": 128, 
   "score": 134, 
   "taskStats": {
    "g00d_b0y": {
     "points": 84, 
     "time": 1573264485
    }, 
    "the_last_resort": {
     "points": 50, 
     "time": 1573264381
    }
   }, 
   "team": "epist"
  }, 
  {
   "lastAccept": 1573268317, 
   "pos": 129, 
   "score": 134, 
   "taskStats": {
    "g00d_b0y": {
     "points": 84, 
     "time": 1573268317
    }, 
    "the_last_resort": {
     "points": 50, 
     "time": 1573233492
    }
   }, 
   "team": "warlock_rootx"
  }, 
  {
   "lastAccept": 1573268624, 
   "pos": 130, 
   "score": 134, 
   "taskStats": {
    "g00d_b0y": {
     "points": 84, 
     "time": 1573268624
    }, 
    "the_last_resort": {
     "points": 50, 
     "time": 1573267989
    }
   }, 
   "team": "TuX"
  }, 
  {
   "lastAccept": 1573270097, 
   "pos": 131, 
   "score": 134, 
   "taskStats": {
    "g00d_b0y": {
     "points": 84, 
     "time": 1573270097
    }, 
    "the_last_resort": {
     "points": 50, 
     "time": 1573269993
    }
   }, 
   "team": "GRIS"
  }, 
  {
   "lastAccept": 1573270310, 
   "pos": 132, 
   "score": 134, 
   "taskStats": {
    "g00d_b0y": {
     "points": 84, 
     "time": 1573270310
    }, 
    "the_last_resort": {
     "points": 50, 
     "time": 1573264872
    }
   }, 
   "team": "wrylynx"
  }, 
  {
   "lastAccept": 1573275369, 
   "pos": 133, 
   "score": 134, 
   "taskStats": {
    "g00d_b0y": {
     "points": 84, 
     "time": 1573275369
    }, 
    "the_last_resort": {
     "points": 50, 
     "time": 1573274652
    }
   }, 
   "team": "\u0430\u043f\u0435\u043b\u044c\u0441\u0438\u043d"
  }, 
  {
   "lastAccept": 1573276213, 
   "pos": 134, 
   "score": 134, 
   "taskStats": {
    "g00d_b0y": {
     "points": 84, 
     "time": 1573276213
    }, 
    "the_last_resort": {
     "points": 50, 
     "time": 1573275837
    }
   }, 
   "team": "kiona"
  }, 
  {
   "lastAccept": 1573281294, 
   "pos": 135, 
   "score": 134, 
   "taskStats": {
    "g00d_b0y": {
     "points": 84, 
     "time": 1573281294
    }, 
    "the_last_resort": {
     "points": 50, 
     "time": 1573279553
    }
   }, 
   "team": "runn3r5"
  }, 
  {
   "lastAccept": 1573285675, 
   "pos": 136, 
   "score": 134, 
   "taskStats": {
    "g00d_b0y": {
     "points": 84, 
     "time": 1573285675
    }, 
    "the_last_resort": {
     "points": 50, 
     "time": 1573285045
    }
   }, 
   "team": "Pwn October"
  }, 
  {
   "lastAccept": 1573286269, 
   "pos": 137, 
   "score": 134, 
   "taskStats": {
    "g00d_b0y": {
     "points": 84, 
     "time": 1573286269
    }, 
    "the_last_resort": {
     "points": 50, 
     "time": 1573286054
    }
   }, 
   "team": "ekawa"
  }, 
  {
   "lastAccept": 1573286466, 
   "pos": 138, 
   "score": 134, 
   "taskStats": {
    "g00d_b0y": {
     "points": 84, 
     "time": 1573286466
    }, 
    "the_last_resort": {
     "points": 50, 
     "time": 1573286241
    }
   }, 
   "team": "Vampire"
  }, 
  {
   "lastAccept": 1573289556, 
   "pos": 139, 
   "score": 134, 
   "taskStats": {
    "g00d_b0y": {
     "points": 84, 
     "time": 1573289556
    }, 
    "the_last_resort": {
     "points": 50, 
     "time": 1573289433
    }
   }, 
   "team": "MATE"
  }, 
  {
   "lastAccept": 1573292321, 
   "pos": 140, 
   "score": 134, 
   "taskStats": {
    "g00d_b0y": {
     "points": 84, 
     "time": 1573292321
    }, 
    "the_last_resort": {
     "points": 50, 
     "time": 1573233467
    }
   }, 
   "team": "sw1ss"
  }, 
  {
   "lastAccept": 1573294636, 
   "pos": 141, 
   "score": 134, 
   "taskStats": {
    "g00d_b0y": {
     "points": 84, 
     "time": 1573294636
    }, 
    "the_last_resort": {
     "points": 50, 
     "time": 1573290248
    }
   }, 
   "team": "ZoiDiCabra"
  }, 
  {
   "lastAccept": 1573296068, 
   "pos": 142, 
   "score": 134, 
   "taskStats": {
    "g00d_b0y": {
     "points": 84, 
     "time": 1573296068
    }, 
    "the_last_resort": {
     "points": 50, 
     "time": 1573295709
    }
   }, 
   "team": "Stack"
  }, 
  {
   "lastAccept": 1573297365, 
   "pos": 143, 
   "score": 134, 
   "taskStats": {
    "g00d_b0y": {
     "points": 84, 
     "time": 1573297365
    }, 
    "the_last_resort": {
     "points": 50, 
     "time": 1573292912
    }
   }, 
   "team": "NIS"
  }, 
  {
   "lastAccept": 1573297382, 
   "pos": 144, 
   "score": 134, 
   "taskStats": {
    "g00d_b0y": {
     "points": 84, 
     "time": 1573297382
    }, 
    "the_last_resort": {
     "points": 50, 
     "time": 1573296960
    }
   }, 
   "team": "mritunjay"
  }, 
  {
   "lastAccept": 1573297947, 
   "pos": 145, 
   "score": 134, 
   "taskStats": {
    "g00d_b0y": {
     "points": 84, 
     "time": 1573297947
    }, 
    "the_last_resort": {
     "points": 50, 
     "time": 1573231866
    }
   }, 
   "team": "CL4IR"
  }, 
  {
   "lastAccept": 1573300556, 
   "pos": 146, 
   "score": 134, 
   "taskStats": {
    "g00d_b0y": {
     "points": 84, 
     "time": 1573300556
    }, 
    "the_last_resort": {
     "points": 50, 
     "time": 1573239484
    }
   }, 
   "team": "TheShellCode"
  }, 
  {
   "lastAccept": 1573304110, 
   "pos": 147, 
   "score": 134, 
   "taskStats": {
    "g00d_b0y": {
     "points": 84, 
     "time": 1573304110
    }, 
    "the_last_resort": {
     "points": 50, 
     "time": 1573294543
    }
   }, 
   "team": "GranolaSport"
  }, 
  {
   "lastAccept": 1573316486, 
   "pos": 148, 
   "score": 134, 
   "taskStats": {
    "g00d_b0y": {
     "points": 84, 
     "time": 1573316486
    }, 
    "the_last_resort": {
     "points": 50, 
     "time": 1573303015
    }
   }, 
   "team": "sexpulapistol"
  }, 
  {
   "lastAccept": 1573327285, 
   "pos": 149, 
   "score": 134, 
   "taskStats": {
    "g00d_b0y": {
     "points": 84, 
     "time": 1573327285
    }, 
    "the_last_resort": {
     "points": 50, 
     "time": 1573319933
    }
   }, 
   "team": "L0gRe4d3rZ"
  }, 
  {
   "lastAccept": 1573327415, 
   "pos": 150, 
   "score": 134, 
   "taskStats": {
    "g00d_b0y": {
     "points": 84, 
     "time": 1573327206
    }, 
    "the_last_resort": {
     "points": 50, 
     "time": 1573327415
    }
   }, 
   "team": "p4010"
  }, 
  {
   "lastAccept": 1573328642, 
   "pos": 151, 
   "score": 134, 
   "taskStats": {
    "g00d_b0y": {
     "points": 84, 
     "time": 1573328642
    }, 
    "the_last_resort": {
     "points": 50, 
     "time": 1573324402
    }
   }, 
   "team": "rwr"
  }, 
  {
   "lastAccept": 1573332085, 
   "pos": 152, 
   "score": 134, 
   "taskStats": {
    "g00d_b0y": {
     "points": 84, 
     "time": 1573332085
    }, 
    "the_last_resort": {
     "points": 50, 
     "time": 1573326466
    }
   }, 
   "team": "BuffOverFlows"
  }, 
  {
   "lastAccept": 1573336360, 
   "pos": 153, 
   "score": 134, 
   "taskStats": {
    "g00d_b0y": {
     "points": 84, 
     "time": 1573336360
    }, 
    "the_last_resort": {
     "points": 50, 
     "time": 1573336036
    }
   }, 
   "team": "NULLKrypt3rs"
  }, 
  {
   "lastAccept": 1573232900, 
   "pos": 154, 
   "score": 84, 
   "taskStats": {
    "g00d_b0y": {
     "points": 84, 
     "time": 1573232900
    }
   }, 
   "team": "[c0rrupted_6ata]"
  }, 
  {
   "lastAccept": 1573231280, 
   "pos": 155, 
   "score": 50, 
   "taskStats": {
    "the_last_resort": {
     "points": 50, 
     "time": 1573231280
    }
   }, 
   "team": "Dragon Sector"
  }, 
  {
   "lastAccept": 1573231552, 
   "pos": 156, 
   "score": 50, 
   "taskStats": {
    "the_last_resort": {
     "points": 50, 
     "time": 1573231552
    }
   }, 
   "team": "AraraAzul"
  }, 
  {
   "lastAccept": 1573231637, 
   "pos": 157, 
   "score": 50, 
   "taskStats": {
    "the_last_resort": {
     "points": 50, 
     "time": 1573231637
    }
   }, 
   "team": "TWN"
  }, 
  {
   "lastAccept": 1573231994, 
   "pos": 158, 
   "score": 50, 
   "taskStats": {
    "the_last_resort": {
     "points": 50, 
     "time": 1573231994
    }
   }, 
   "team": "cratox"
  }, 
  {
   "lastAccept": 1573232264, 
   "pos": 159, 
   "score": 50, 
   "taskStats": {
    "the_last_resort": {
     "points": 50, 
     "time": 1573232264
    }
   }, 
   "team": "caillou"
  }, 
  {
   "lastAccept": 1573232499, 
   "pos": 160, 
   "score": 50, 
   "taskStats": {
    "the_last_resort": {
     "points": 50, 
     "time": 1573232499
    }
   }, 
   "team": "wildcat"
  }, 
  {
   "lastAccept": 1573232669, 
   "pos": 161, 
   "score": 50, 
   "taskStats": {
    "the_last_resort": {
     "points": 50, 
     "time": 1573232669
    }
   }, 
   "team": "Pystyy Vet\u00e4\u00e4"
  }, 
  {
   "lastAccept": 1573233024, 
   "pos": 162, 
   "score": 50, 
   "taskStats": {
    "the_last_resort": {
     "points": 50, 
     "time": 1573233024
    }
   }, 
   "team": "sotto_i_pwnti"
  }, 
  {
   "lastAccept": 1573233689, 
   "pos": 163, 
   "score": 50, 
   "taskStats": {
    "the_last_resort": {
     "points": 50, 
     "time": 1573233689
    }
   }, 
   "team": "__T3TR4H3DR0N__"
  }, 
  {
   "lastAccept": 1573233727, 
   "pos": 164, 
   "score": 50, 
   "taskStats": {
    "the_last_resort": {
     "points": 50, 
     "time": 1573233727
    }
   }, 
   "team": "luxlooters"
  }, 
  {
   "lastAccept": 1573233789, 
   "pos": 165, 
   "score": 50, 
   "taskStats": {
    "the_last_resort": {
     "points": 50, 
     "time": 1573233789
    }
   }, 
   "team": "dimanonim"
  }, 
  {
   "lastAccept": 1573236513, 
   "pos": 166, 
   "score": 50, 
   "taskStats": {
    "the_last_resort": {
     "points": 50, 
     "time": 1573236513
    }
   }, 
   "team": "KRAL"
  }, 
  {
   "lastAccept": 1573236647, 
   "pos": 167, 
   "score": 50, 
   "taskStats": {
    "the_last_resort": {
     "points": 50, 
     "time": 1573236647
    }
   }, 
   "team": "EvilBunnyWrote"
  }, 
  {
   "lastAccept": 1573237106, 
   "pos": 168, 
   "score": 50, 
   "taskStats": {
    "the_last_resort": {
     "points": 50, 
     "time": 1573237106
    }
   }, 
   "team": "Double Standard CTF"
  }, 
  {
   "lastAccept": 1573239501, 
   "pos": 169, 
   "score": 50, 
   "taskStats": {
    "the_last_resort": {
     "points": 50, 
     "time": 1573239501
    }
   }, 
   "team": "Whitefang"
  }, 
  {
   "lastAccept": 1573240427, 
   "pos": 170, 
   "score": 50, 
   "taskStats": {
    "the_last_resort": {
     "points": 50, 
     "time": 1573240427
    }
   }, 
   "team": "smallkirby"
  }, 
  {
   "lastAccept": 1573240516, 
   "pos": 171, 
   "score": 50, 
   "taskStats": {
    "the_last_resort": {
     "points": 50, 
     "time": 1573240516
    }
   }, 
   "team": "BatamansKitchen"
  }, 
  {
   "lastAccept": 1573241380, 
   "pos": 172, 
   "score": 50, 
   "taskStats": {
    "the_last_resort": {
     "points": 50, 
     "time": 1573241380
    }
   }, 
   "team": "The Additional Payphones"
  }, 
  {
   "lastAccept": 1573241975, 
   "pos": 173, 
   "score": 50, 
   "taskStats": {
    "the_last_resort": {
     "points": 50, 
     "time": 1573241975
    }
   }, 
   "team": "Bigos"
  }, 
  {
   "lastAccept": 1573242860, 
   "pos": 174, 
   "score": 50, 
   "taskStats": {
    "the_last_resort": {
     "points": 50, 
     "time": 1573242860
    }
   }, 
   "team": "0x0d1n"
  }, 
  {
   "lastAccept": 1573248393, 
   "pos": 175, 
   "score": 50, 
   "taskStats": {
    "the_last_resort": {
     "points": 50, 
     "time": 1573248393
    }
   }, 
   "team": "CHC"
  }, 
  {
   "lastAccept": 1573248785, 
   "pos": 176, 
   "score": 50, 
   "taskStats": {
    "the_last_resort": {
     "points": 50, 
     "time": 1573248785
    }
   }, 
   "team": "vitatvill"
  }, 
  {
   "lastAccept": 1573249014, 
   "pos": 177, 
   "score": 50, 
   "taskStats": {
    "the_last_resort": {
     "points": 50, 
     "time": 1573249014
    }
   }, 
   "team": "byrdpm"
  }, 
  {
   "lastAccept": 1573249125, 
   "pos": 178, 
   "score": 50, 
   "taskStats": {
    "the_last_resort": {
     "points": 50, 
     "time": 1573249125
    }
   }, 
   "team": "Ligma"
  }, 
  {
   "lastAccept": 1573249618, 
   "pos": 179, 
   "score": 50, 
   "taskStats": {
    "the_last_resort": {
     "points": 50, 
     "time": 1573249618
    }
   }, 
   "team": "EVA"
  }, 
  {
   "lastAccept": 1573251944, 
   "pos": 180, 
   "score": 50, 
   "taskStats": {
    "the_last_resort": {
     "points": 50, 
     "time": 1573251944
    }
   }, 
   "team": "APA Razi"
  }, 
  {
   "lastAccept": 1573253406, 
   "pos": 181, 
   "score": 50, 
   "taskStats": {
    "the_last_resort": {
     "points": 50, 
     "time": 1573253406
    }
   }, 
   "team": "WkRKVloyRkhSakJhVTBKcUNnPT0K"
  }, 
  {
   "lastAccept": 1573255541, 
   "pos": 182, 
   "score": 50, 
   "taskStats": {
    "the_last_resort": {
     "points": 50, 
     "time": 1573255541
    }
   }, 
   "team": "Bananas de terno"
  }, 
  {
   "lastAccept": 1573256237, 
   "pos": 183, 
   "score": 50, 
   "taskStats": {
    "the_last_resort": {
     "points": 50, 
     "time": 1573256237
    }
   }, 
   "team": "bootplug"
  }, 
  {
   "lastAccept": 1573256860, 
   "pos": 184, 
   "score": 50, 
   "taskStats": {
    "the_last_resort": {
     "points": 50, 
     "time": 1573256860
    }
   }, 
   "team": "Zeus WPI"
  }, 
  {
   "lastAccept": 1573260070, 
   "pos": 185, 
   "score": 50, 
   "taskStats": {
    "the_last_resort": {
     "points": 50, 
     "time": 1573260070
    }
   }, 
   "team": "Wani Hackase"
  }, 
  {
   "lastAccept": 1573260176, 
   "pos": 186, 
   "score": 50, 
   "taskStats": {
    "the_last_resort": {
     "points": 50, 
     "time": 1573260176
    }
   }, 
   "team": "Steam Locomotive"
  }, 
  {
   "lastAccept": 1573263879, 
   "pos": 187, 
   "score": 50, 
   "taskStats": {
    "the_last_resort": {
     "points": 50, 
     "time": 1573263879
    }
   }, 
   "team": "wabisabi"
  }, 
  {
   "lastAccept": 1573268788, 
   "pos": 188, 
   "score": 50, 
   "taskStats": {
    "the_last_resort": {
     "points": 50, 
     "time": 1573268788
    }
   }, 
   "team": "furi"
  }, 
  {
   "lastAccept": 1573270593, 
   "pos": 189, 
   "score": 50, 
   "taskStats": {
    "the_last_resort": {
     "points": 50, 
     "time": 1573270593
    }
   }, 
   "team": "SuperNewbie"
  }, 
  {
   "lastAccept": 1573271114, 
   "pos": 190, 
   "score": 50, 
   "taskStats": {
    "the_last_resort": {
     "points": 50, 
     "time": 1573271114
    }
   }, 
   "team": "HackNinja"
  }, 
  {
   "lastAccept": 1573273075, 
   "pos": 191, 
   "score": 50, 
   "taskStats": {
    "the_last_resort": {
     "points": 50, 
     "time": 1573273075
    }
   }, 
   "team": "c6a7"
  }, 
  {
   "lastAccept": 1573277139, 
   "pos": 192, 
   "score": 50, 
   "taskStats": {
    "the_last_resort": {
     "points": 50, 
     "time": 1573277139
    }
   }, 
   "team": "goldisgreen"
  }, 
  {
   "lastAccept": 1573277196, 
   "pos": 193, 
   "score": 50, 
   "taskStats": {
    "the_last_resort": {
     "points": 50, 
     "time": 1573277196
    }
   }, 
   "team": "Unicr0n"
  }, 
  {
   "lastAccept": 1573291894, 
   "pos": 194, 
   "score": 50, 
   "taskStats": {
    "the_last_resort": {
     "points": 50, 
     "time": 1573291894
    }
   }, 
   "team": "PwnBr0s"
  }, 
  {
   "lastAccept": 1573293783, 
   "pos": 195, 
   "score": 50, 
   "taskStats": {
    "the_last_resort": {
     "points": 50, 
     "time": 1573293783
    }
   }, 
   "team": "ustadYUSUF"
  }, 
  {
   "lastAccept": 1573297530, 
   "pos": 196, 
   "score": 50, 
   "taskStats": {
    "the_last_resort": {
     "points": 50, 
     "time": 1573297530
    }
   }, 
   "team": "413x01"
  }, 
  {
   "lastAccept": 1573298022, 
   "pos": 197, 
   "score": 50, 
   "taskStats": {
    "the_last_resort": {
     "points": 50, 
     "time": 1573298022
    }
   }, 
   "team": "flatbrew coalition"
  }, 
  {
   "lastAccept": 1573303177, 
   "pos": 198, 
   "score": 50, 
   "taskStats": {
    "the_last_resort": {
     "points": 50, 
     "time": 1573303177
    }
   }, 
   "team": "0x1"
  }, 
  {
   "lastAccept": 1573308313, 
   "pos": 199, 
   "score": 50, 
   "taskStats": {
    "the_last_resort": {
     "points": 50, 
     "time": 1573308313
    }
   }, 
   "team": "4lk4x0f4"
  }, 
  {
   "lastAccept": 1573310158, 
   "pos": 200, 
   "score": 50, 
   "taskStats": {
    "the_last_resort": {
     "points": 50, 
     "time": 1573310158
    }
   }, 
   "team": "trenchesofit"
  }, 
  {
   "lastAccept": 1573313601, 
   "pos": 201, 
   "score": 50, 
   "taskStats": {
    "the_last_resort": {
     "points": 50, 
     "time": 1573313601
    }
   }, 
   "team": "chiba"
  }, 
  {
   "lastAccept": 1573318236, 
   "pos": 202, 
   "score": 50, 
   "taskStats": {
    "the_last_resort": {
     "points": 50, 
     "time": 1573318236
    }
   }, 
   "team": "MYAGER"
  }, 
  {
   "lastAccept": 1573318354, 
   "pos": 203, 
   "score": 50, 
   "taskStats": {
    "the_last_resort": {
     "points": 50, 
     "time": 1573318354
    }
   }, 
   "team": "wine"
  }, 
  {
   "lastAccept": 1573319970, 
   "pos": 204, 
   "score": 50, 
   "taskStats": {
    "the_last_resort": {
     "points": 50, 
     "time": 1573319970
    }
   }, 
   "team": "Tortoise"
  }, 
  {
   "lastAccept": 1573324779, 
   "pos": 205, 
   "score": 50, 
   "taskStats": {
    "the_last_resort": {
     "points": 50, 
     "time": 1573324779
    }
   }, 
   "team": "Jennycitos"
  }, 
  {
   "lastAccept": 1573340341, 
   "pos": 206, 
   "score": 50, 
   "taskStats": {
    "the_last_resort": {
     "points": 50, 
     "time": 1573340341
    }
   }, 
   "team": "Mars Explorer"
  }, 
  {
   "lastAccept": 1573343109, 
   "pos": 207, 
   "score": 50, 
   "taskStats": {
    "the_last_resort": {
     "points": 50, 
     "time": 1573343109
    }
   }, 
   "team": "ScarletAndGrey"
  }
 ], 
 "tasks": [
  "g00d_b0y", 
  "the_last_resort", 
  "full_troll", 
  "future_message_pt1", 
  "random_vault", 
  "roots_before_branches", 
  "cloud_admin", 
  "real_ec", 
  "i_shall_never_be_anything", 
  "random_crypto", 
  "future_message_pt2", 
  "future_message_pt3", 
  "astrobot", 
  "baby_recruiter", 
  "future_message_pt4", 
  "hardware_trojan_pt1", 
  "rmbellious", 
  "federated_sophia", 
  "vamos_pra_russia", 
  "matroska"
 ]
}